[
  {
    "employer_name": "IBM",
    "job_title": "Semiconductor Software Product Manager",
    "job_city": "Albany",
    "job_state": "US",
    "job_posted_at": "Recently",
    "job_description": "Data Science job for the role Semiconductor Software Product Manager at ProfessionalAlbany, US",
    "job_apply_link": "https://ibmglobal.avature.net/en_US/careers/JobDetail?jobId=57841&source=WEB_Search_NA",
    "id": "ibm-semiconductor-software-product-manager-albany"
  },
  {
    "employer_name": "IBM",
    "job_title": "2026 Intern – Visual Designer",
    "job_city": "Austin",
    "job_state": "US",
    "job_posted_at": "Recently",
    "job_description": "Data Science job for the role 2026 Intern – Visual Designer at InternshipAustin, US",
    "job_apply_link": "https://ibmglobal.avature.net/en_US/careers/JobDetail?jobId=58182&source=WEB_Search_NA",
    "id": "ibm-2026-intern-visual-designer-austin"
  },
  {
    "employer_name": "SIEMENS",
    "job_title": "Remote Services Project Manager - Navy Control Systems",
    "job_city": "Arlington",
    "job_state": "United States of America",
    "job_posted_at": "Recently",
    "job_description": "Data Science job for the role Remote Services Project Manager - Navy Control Systems at Arlington, Virginia, United States of America",
    "job_apply_link": "https://jobs.siemens.com/careers?query=Data%20Science&location=USA&pid=563156126459716&domain=siemens.com&sort_by=relevance&triggerGoButton=false&utm_source=j_c_us",
    "id": "siemens-remote-services-project-manager-navy-control-systems-arlington"
  }
]