[
  {
    "employer_name": "Arm",
    "job_title": "Manager, Product Marketing Infrastructure",
    "job_city": "San Jose",
    "job_state": "California",
    "job_posted_at": "Recently",
    "job_description": "Data Science job for the role Senior Manager, Product Marketing Infrastructure at San Jose, California",
    "job_apply_link": "https://careers.arm.com/job/san-jose/senior-manager-product-marketing-infrastructure/33099/81809909920",
    "id": "arm-manager-product-marketing-infrastructure-san-jose"
  }
]