[
  {
    "employer_name": "ABB",
    "job_title": "HSE Management System Analyst",
    "job_city": "Multiple",
    "job_state": "Various",
    "job_posted_at": "Today",
    "job_description": "Data Science job for the role HSE Management System Analyst at Available in one of 2 s",
    "job_apply_link": "https://careers.abb/global/en/job/JR00019842/HSE-Management-System-Analyst",
    "id": "abb-hse-management-system-analyst-multiple"
  },
  {
    "employer_name": "ABB",
    "job_title": "Senior HSE Auditor",
    "job_city": "Multiple",
    "job_state": "Various",
    "job_posted_at": "Today",
    "job_description": "Data Science job for the role Senior HSE Auditor at Available in one of 3 s",
    "job_apply_link": "https://careers.abb/global/en/job/JR00019841/Senior-HSE-Auditor",
    "id": "abb-senior-hse-auditor-multiple"
  }
]