[
  {
    "employer_name": "IBM",
    "job_title": "Enterprise Database Architect Lead",
    "job_city": "San Jose",
    "job_state": "US",
    "job_posted_at": "Recently",
    "job_description": "Data Science job for the role Enterprise Database Architect Lead at ProfessionalSan Jose, US",
    "job_apply_link": "https://ibmglobal.avature.net/en_US/careers/JobDetail?jobId=84020&source=WEB_Search_NA",
    "id": "ibm-enterprise-database-architect-lead-san-jose"
  },
  {
    "employer_name": "ANALOG DEVICES",
    "job_title": "Quality Systems Engineering Intern",
    "job_city": "US",
    "job_state": "MA",
    "job_posted_at": "Posted Yesterday",
    "job_description": "Data Science job for the role Quality Systems Engineering Intern at US, MA, Wilmington",
    "job_apply_link": "https://analogdevices.wd1.myworkdayjobs.com/en-US/External/job/US-MA-Wilmington/Quality-Systems-Engineering-Intern_R257847?q=Data+Science&locationCountry=bc33aa3152ec42d4995f4791a106ed09",
    "id": "analog-devices-quality-systems-engineering-intern-us"
  }
]