[
  {
    "employer_name": "Microsoft",
    "job_title": "MAI Monetization",
    "job_city": "Mountain View",
    "job_state": "California",
    "job_posted_at": "Recently",
    "job_description": "Category: Principal Product Manager. Level: All Levels. Posted: Recently. Full Title: Principal Product Manager - MAI Monetization",
    "job_apply_link": "https://jobs.careers.microsoft.com/global/en/job/1878043/Principal-Product-Manager---MAI-Monetization",
    "id": "microsoft-mai-monetization-mountain-view"
  },
  {
    "employer_name": "Arm",
    "job_title": "DCIM Engineer",
    "job_city": "Austin",
    "job_state": "Texas",
    "job_posted_at": "Recently",
    "job_description": "Data Science job for the role Principal DCIM Engineer at Austin, Texas",
    "job_apply_link": "https://careers.arm.com/job/austin/principal-dcim-engineer/33099/83212077936",
    "id": "arm-dcim-engineer-austin"
  },
  {
    "employer_name": "Arm",
    "job_title": "Senior/Staff/Principle SoC Design Engineer",
    "job_city": "Cambridge",
    "job_state": "United Kingdom",
    "job_posted_at": "Recently",
    "job_description": "Data Science job for the role Senior/Staff/Principle SoC Design Engineer at Cambridge, United Kingdom",
    "job_apply_link": "https://careers.arm.com/job/cambridge/senior-staff-principle-soc-design-engineer/33099/84085082208",
    "id": "arm-senior-staff-principle-soc-design-engineer-cambridge"
  }
]