[
  {
    "employer_name": "Google",
    "job_title": "Strategy and Operations Analyst",
    "job_city": "New York",
    "job_state": "NY",
    "job_posted_at": "Recently",
    "job_description": "19 Category: Data Science. Level: corporate_fareGoogle. Posted: Recently. Full Title: Strategy and Operations Analyst, Go-to-Market",
    "job_apply_link": "https://www.google.com/about/careers/applications/jobs/results/88201908308583110-strategy-and-operations-analyst-gotomarket?q=%22Data+Science%22&location=United+States&target_level=INTERN_AND_APPRENTICE&target_level=EARLY&target_level=ADVANCED&target_level=MID&degree=MASTERS&degree=ASSOCIATE&degree=BACHELORS&employment_type=TEMPORARY&employment_type=INTERN&employment_type=PART_TIME&employment_type=FULL_TIME",
    "id": "google-strategy-and-operations-analyst-new-york"
  },
  {
    "employer_name": "Arm",
    "job_title": "Thermo-Mechanical Engineer",
    "job_city": "San Jose",
    "job_state": "California",
    "job_posted_at": "Recently",
    "job_description": "Data Science job for the role Principal Thermo-Mechanical Engineer at San Jose, California",
    "job_apply_link": "https://careers.arm.com/job/san-jose/principal-thermo-mechanical-engineer/33099/84709712816",
    "id": "arm-thermo-mechanical-engineer-san-jose"
  },
  {
    "employer_name": "AiJobs",
    "job_title": "Health Data Scientist",
    "job_city": "US",
    "job_state": "FL",
    "job_posted_at": "4d ago",
    "job_description": "data science job for the role Health Data Scientist at Jupiter, FL, US",
    "job_apply_link": "https://www.aijobs.com/jobs/153703945-health-data-scientist",
    "id": "aijobs-health-data-scientist-us"
  },
  {
    "employer_name": "AiJobs",
    "job_title": "Jr. Data Scientist - Austin, Jr. Developer Program",
    "job_city": "US",
    "job_state": "TX",
    "job_posted_at": "4h ago",
    "job_description": "data science job for the role Jr. Data Scientist - Austin, Jr. Developer Program at Austin, TX, US",
    "job_apply_link": "https://www.aijobs.com/jobs/153703926-jr-data-scientist-austin-jr-developer-program",
    "id": "aijobs-jr-data-scientist-austin-jr-developer-program-us"
  },
  {
    "employer_name": "AiJobs",
    "job_title": "Applied Scientist",
    "job_city": "US",
    "job_state": "CA",
    "job_posted_at": "1d ago",
    "job_description": "data science job for the role Senior Applied Scientist at Sunnyvale, CA, US",
    "job_apply_link": "https://www.aijobs.com/jobs/153703933-senior-applied-scientist",
    "id": "aijobs-applied-scientist-us"
  },
  {
    "employer_name": "AiJobs",
    "job_title": "Data Scientist - Platform Intelligence",
    "job_city": "US",
    "job_state": "CA",
    "job_posted_at": "16h ago",
    "job_description": "data science job for the role Data Scientist - Platform Intelligence at Mountain View, CA, US",
    "job_apply_link": "https://www.aijobs.com/jobs/153703919-data-scientist-platform-intelligence",
    "id": "aijobs-data-scientist-platform-intelligence-us"
  },
  {
    "employer_name": "AiJobs",
    "job_title": "Data Scientist - Commercial Pharmaceuticals",
    "job_city": "US",
    "job_state": "MA",
    "job_posted_at": "4d ago",
    "job_description": "data science job for the role Data Scientist - Commercial Pharmaceuticals at Cambridge, MA, US",
    "job_apply_link": "https://www.aijobs.com/jobs/153703927-data-scientist-commercial-pharmaceuticals",
    "id": "aijobs-data-scientist-commercial-pharmaceuticals-us"
  },
  {
    "employer_name": "AiJobs",
    "job_title": "AI / Machine Learning Engineer",
    "job_city": "US",
    "job_state": "CA",
    "job_posted_at": "4d ago",
    "job_description": "data science job for the role AI / Machine Learning Engineer at Santa Monica, CA, US",
    "job_apply_link": "https://www.aijobs.com/jobs/153703932-ai-machine-learning-engineer",
    "id": "aijobs-ai-machine-learning-engineer-us"
  },
  {
    "employer_name": "AiJobs",
    "job_title": "AI/ML Machine Learning Engineer",
    "job_city": "US",
    "job_state": "PA",
    "job_posted_at": "12h ago",
    "job_description": "data science job for the role AI/ML Machine Learning Engineer at Herndon, PA, US",
    "job_apply_link": "https://www.aijobs.com/jobs/153703939-ai-ml-machine-learning-engineer",
    "id": "aijobs-ai-ml-machine-learning-engineer-us"
  },
  {
    "employer_name": "AiJobs",
    "job_title": "Data Scientist Intern - Digital and Technology Partners",
    "job_city": "US",
    "job_state": "NY",
    "job_posted_at": "1d ago",
    "job_description": "data science job for the role Data Scientist Intern - Digital and Technology Partners - Hybrid at New York, NY, US",
    "job_apply_link": "https://www.aijobs.com/jobs/153703924-data-scientist-intern-digital-and-technology-partners-hybrid",
    "id": "aijobs-data-scientist-intern-digital-and-technology-partners-us"
  },
  {
    "employer_name": "AiJobs",
    "job_title": "Data Scientist – Machine Learning & Statistical Evaluation",
    "job_city": "US",
    "job_state": "CA",
    "job_posted_at": "3d ago",
    "job_description": "data science job for the role Data Scientist – Machine Learning & Statistical Evaluation at Palo Alto, CA, US",
    "job_apply_link": "https://www.aijobs.com/jobs/153703942-data-scientist-machine-learning-statistical-evaluation",
    "id": "aijobs-data-scientist-machine-learning-statistical-evaluation-us"
  },
  {
    "employer_name": "AiJobs",
    "job_title": "Artificial Intelligence / Machine Learning Research Engineer",
    "job_city": "US",
    "job_state": "PA",
    "job_posted_at": "1d ago",
    "job_description": "data science job for the role Artificial Intelligence / Machine Learning Research Engineer at Springfield, PA, US",
    "job_apply_link": "https://www.aijobs.com/jobs/153703940-artificial-intelligence-machine-learning-research-engineer",
    "id": "aijobs-artificial-intelligence-machine-learning-research-engineer-us"
  },
  {
    "employer_name": "AiJobs",
    "job_title": "Data Scientist / Senior Data Scientist, Analytics",
    "job_city": "US",
    "job_state": "DC",
    "job_posted_at": "3d ago",
    "job_description": "data science job for the role Data Scientist / Senior Data Scientist, Analytics at Washington, DC, US",
    "job_apply_link": "https://www.aijobs.com/jobs/153703936-data-scientist-senior-data-scientist-analytics",
    "id": "aijobs-data-scientist-senior-data-scientist-analytics-us"
  },
  {
    "employer_name": "AiJobs",
    "job_title": "Research/AI Scientist",
    "job_city": "US",
    "job_state": "CA",
    "job_posted_at": "4d ago",
    "job_description": "data science job for the role Research/AI Scientist at San Francisco, CA, US",
    "job_apply_link": "https://www.aijobs.com/jobs/153703931-research-ai-scientist",
    "id": "aijobs-research-ai-scientist-us"
  }
]