[
  {
    "job_title": "Applied Scientist, Artificial General Intelligence",
    "employer_name": "Amazon",
    "job_city": "Bellevue",
    "job_state": "WA",
    "job_description": "Data Science job for the role Applied Scientist, Artificial General Intelligence at Bellevue, WA, USA",
    "job_apply_link": "https://amazon.jobs/en-gb/jobs/3071222/applied-scientist-artificial-general-intelligence",
    "job_posted_at": "2025-09-02T00:00:00.000Z",
    "job_posted_at_datetime_utc": "2025-09-02T00:00:00.000Z",
    "id": "amazon-applied-scientist-artificial-general-intelligence-bellevue"
  },
  {
    "job_title": "Deep Learning Architect, Generative AI Innovation Center",
    "employer_name": "Amazon",
    "job_city": "New York",
    "job_state": "NY",
    "job_description": "Data Science job for the role Deep Learning Architect, Generative AI Innovation Center at New York, NY, USA",
    "job_apply_link": "https://amazon.jobs/en-gb/jobs/3071234/deep-learning-architect-generative-ai-innovation-center",
    "job_posted_at": "2025-09-02T00:00:00.000Z",
    "job_posted_at_datetime_utc": "2025-09-02T00:00:00.000Z",
    "id": "amazon-deep-learning-architect-generative-ai-innovation-center-new-york"
  },
  {
    "employer_name": "Arm",
    "job_title": "Software Engineer - Linux Kernel",
    "job_city": "Cambridge",
    "job_state": "United Kingdom",
    "job_posted_at": "Recently",
    "job_description": "Data Science job for the role Principal Software Engineer - Linux Kernel at Cambridge, United Kingdom",
    "job_apply_link": "https://careers.arm.com/job/cambridge/principal-software-engineer-linux-kernel/33099/84081698816",
    "id": "arm-software-engineer-linux-kernel-cambridge"
  },
  {
    "employer_name": "Arm",
    "job_title": "System Level Product Engineer",
    "job_city": "Austin",
    "job_state": "Texas",
    "job_posted_at": "Recently",
    "job_description": "Data Science job for the role Staff System Level Product Engineer at Austin, Texas",
    "job_apply_link": "https://careers.arm.com/job/austin/staff-system-level-product-engineer/33099/85702733840",
    "id": "arm-system-level-product-engineer-austin"
  }
]