[
  {
    "employer_name": "ABB",
    "job_title": "HRXP Compensation & Performance Experience Lead",
    "job_city": "Multiple",
    "job_state": "Various",
    "job_posted_at": "Today",
    "job_description": "Data Science job for the role HRXP Compensation & Performance Experience Lead at Available in one of 21 s",
    "job_apply_link": "https://careers.abb/global/en/job/JR00020171/HRXP-Compensation-Performance-Experience-Lead",
    "id": "abb-hrxp-compensation-performance-experience-lead-multiple"
  }
]